CHANGES
COPYING
README
ez_setup.py
setup.py
palabra.egg-info/PKG-INFO
palabra.egg-info/SOURCES.txt
palabra.egg-info/dependency_links.txt
palabra.egg-info/entry_points.txt
palabra.egg-info/not-zip-safe
palabra.egg-info/top_level.txt
palabralib/__init__.py
palabralib/action.py
palabralib/appearance.py
palabralib/clue.py
palabralib/constants.py
palabralib/cpalabra.c
palabralib/cpalabra.h
palabralib/cpalabramodule.c
palabralib/editor.py
palabralib/export.py
palabralib/files.py
palabralib/grid.py
palabralib/gui.py
palabralib/gui_editor.py
palabralib/gui_prefs.py
palabralib/gui_word.py
palabralib/newpuzzle.py
palabralib/pattern.py
palabralib/preferences.py
palabralib/properties.py
palabralib/puzzle.py
palabralib/transform.py
palabralib/view.py
palabralib/word.py
palabralib/resources/icon1.png
palabralib/resources/icon2.png
palabralib/xml/patterns.xml