Metadata-Version: 1.1
Name: palabra
Version: 0.1.6
Summary: A free crossword editor
Home-page: http://bitbucket.org/svisser/palabra
Author: Simeon Visser
Author-email: simeonvisser@gmail.com
License: GNU General Public License (GPL)
Platform: UNKNOWN
Classifier: Development Status :: 4 - Beta
Classifier: Environment :: X11 Applications :: GTK
Classifier: Intended Audience :: End Users/Desktop
Classifier: License :: OSI Approved :: GNU General Public License (GPL)
Classifier: Operating System :: POSIX :: Linux
Classifier: Natural Language :: English
Classifier: Programming Language :: C
Classifier: Programming Language :: Python :: 2.6
Classifier: Topic :: Games/Entertainment :: Puzzle Games
Requires: lxml
